pled-0.1.2.dist-info/METADATA
pled-0.1.2.dist-info/WHEEL
pled-0.1.2.dist-info/licenses/LICENSE
pled/execute.py
pled/__init__.py
pled/_pled.pyi
pled/transform.py
pled/py.typed
pled/_pled.cpython-310-darwin.so
pled-0.1.2.dist-info/RECORD
