Metadata-Version: 2.4
Name: pled
Version: 0.1.2
Classifier: Programming Language :: Rust
Classifier: Programming Language :: Python :: Implementation :: CPython
Classifier: Programming Language :: Python :: Implementation :: PyPy
License-File: LICENSE
Summary: print-less debugging
License: Apache-2.0
Requires-Python: >=3.10
